mcp_openai_image_generation/__init__.py
mcp_openai_image_generation/app.py
mcp_openai_image_generation/cli.py
mcp_openai_image_generation-0.1.0.dist-info/METADATA
mcp_openai_image_generation-0.1.0.dist-info/WHEEL
mcp_openai_image_generation-0.1.0.dist-info/entry_points.txt
mcp_openai_image_generation-0.1.0.dist-info/licenses/LICENSE
mcp_openai_image_generation-0.1.0.dist-info/RECORD
