Metadata-Version: 2.4
Name: mcp-openai-image-generation
Version: 0.1.0
Summary: OpenAI image generation MCP server
Project-URL: Repository, https://github.com/ai-zerolab/mcp-openai-image-generation
Author-email: Wh1isper <jizhongsheng957@gmail.com>
License-File: LICENSE
Keywords: python
Classifier: Intended Audience :: Developers
Classifier: Programming Language :: Python
Classifier: Programming Language :: Python :: 3
Classifier: Programming Language :: Python :: 3.10
Classifier: Programming Language :: Python :: 3.11
Classifier: Programming Language :: Python :: 3.12
Classifier: Programming Language :: Python :: 3.13
Classifier: Topic :: Software Development :: Libraries :: Python Modules
Requires-Python: <4.0,>=3.10
Requires-Dist: mcp[cli]>=1.3.0
Requires-Dist: openai>=1.78.1
Requires-Dist: pydantic>=2.11.4
Requires-Dist: typer>=0.15.3
